lazypimp/__init__.py
lazypimp/setup.py
lazypimp-0.1.0.dist-info/LICENSE
lazypimp-0.1.0.dist-info/METADATA
lazypimp-0.1.0.dist-info/WHEEL
lazypimp-0.1.0.dist-info/top_level.txt
lazypimp-0.1.0.dist-info/RECORD
