Metadata-Version: 2.1
Name: lazypimp
Version: 0.1.0
Summary: A Python package to lazy import modules and functions.
Author-email: Silvano Rosenau <silvano.rosenau@uni-hamburg.de>
Project-URL: Repository, https://github.com/Gordi42/lazypimp
Keywords: lazy,import,module,function,package,python,lazypimp
Classifier: Programming Language :: Python :: 3
Classifier: License :: OSI Approved :: MIT License
Classifier: Operating System :: OS Independent
Classifier: Development Status :: 3 - Alpha
Requires-Python: >=3.8
License-File: LICENSE
